MANIFEST.in
setup.cfg
setup.py
django_presence.egg-info/PKG-INFO
django_presence.egg-info/SOURCES.txt
django_presence.egg-info/dependency_links.txt
django_presence.egg-info/not-zip-safe
django_presence.egg-info/requires.txt
django_presence.egg-info/top_level.txt
presence/__init__.py
presence/admin.py
presence/apps.py
presence/conf.py
presence/models.py
presence/tasks.py
presence/tests.py
presence/views.py
presence/go/centpres
presence/go/config.json
presence/go/src/main.go
presence/management/__init__.py
presence/management/conf.py
presence/management/commands/__init__.py
presence/management/commands/installpres.py
presence/migrations/__init__.py
presence/templates/presence/widget.html
presence/templates/presence/js/client.js
presence/templates/presence/js/handlers.js
presence/templates/presence/js/utils.js