Metadata-Version: 1.1
Name: django-presence
Version: 0.2
Summary: User presence widget for Django using Centrifugo
Home-page: https://github.com/synw/django-presence
Author: synw
Author-email: synwe@yahoo.com
License: UNKNOWN
Download-URL: https://github.com/synw/django-presence/releases/tag/0.2
Keywords: django,websockets
Platform: UNKNOWN
Classifier: Development Status :: 3 - Alpha
Classifier: Framework :: Django :: 1.9
Classifier: Intended Audience :: Developers
Classifier: License :: OSI Approved :: MIT License
Classifier: Programming Language :: Python :: 2.7
